andavar/__init__.py
andavar/__main__.py
andavar/code.py
Andavar-0.0.2.dist-info/LICENSE
Andavar-0.0.2.dist-info/METADATA
Andavar-0.0.2.dist-info/WHEEL
Andavar-0.0.2.dist-info/top_level.txt
Andavar-0.0.2.dist-info/RECORD
