Metadata-Version: 2.1
Name: Andavar
Version: 0.0.2
Summary: description of your package
Home-page: https://github.com/ndrohith09/simple_todo_django
Author: rohith
Author-email: ndrohith09@gmail.com
License: MIT
Requires-Python: >=3.6
License-File: LICENSE
Requires-Dist: numpy
